curvlearn/README.md
curvlearn/__init__.py
curvlearn/manifolds/__init__.py
curvlearn/manifolds/euclidean.py
curvlearn/manifolds/geometry.py
curvlearn/manifolds/manifold.py
curvlearn/manifolds/math.py
curvlearn/manifolds/product.py
curvlearn/manifolds/stereographic.py
curvlearn/optimizers/__init__.py
curvlearn/optimizers/radagrad.py
curvlearn/optimizers/radam.py
curvlearn/optimizers/rsgd.py
curvlearn-1.0.1.dist-info/LICENSE
curvlearn-1.0.1.dist-info/WHEEL
curvlearn-1.0.1.dist-info/METADATA
curvlearn-1.0.1.dist-info/RECORD
